mumoco/__init__.py
mumoco/conanbuilder/__init__.py
mumoco/conanbuilder/buildersettings.py
mumoco/conanbuilder/configreader.py
mumoco/conanbuilder/package.py
mumoco/conanbuilder/remote.py
mumoco/conanbuilder/runner.py
mumoco/conanbuilder/signature.py
mumoco/errors.py
mumoco/main.py
mumoco/mumoco_api.py
mumoco-0.3.3.dist-info/entry_points.txt
mumoco-0.3.3.dist-info/LICENSE.txt
mumoco-0.3.3.dist-info/WHEEL
mumoco-0.3.3.dist-info/METADATA
mumoco-0.3.3.dist-info/RECORD
